{
  "data": [
    {
      "date": "2021-01-01",
      "stock_id": "2483",
      "open": 20.2,
      "max": 20.9,
      "min": 19.3,
      "close": 19.3,
      "Trading_Volume": 1973064,
      "Trading_money": 39569619
    },
    {
      "date": "2021-02-01",
      "stock_id": "2483",
      "open": 19.3,
      "max": 20.25,
      "min": 19,
      "close": 20.15,
      "Trading_Volume": 1189154,
      "Trading_money": 23497796
    },
    {
      "date": "2021-03-01",
      "stock_id": "2483",
      "open": 20.45,
      "max": 21.3,
      "min": 19.95,
      "close": 20.2,
      "Trading_Volume": 5344552,
      "Trading_money": 110162981
    },
    {
      "date": "2021-04-01",
      "stock_id": "2483",
      "open": 20.15,
      "max": 23.2,
      "min": 20.1,
      "close": 22.95,
      "Trading_Volume": 8766265,
      "Trading_money": 192350620
    },
    {
      "date": "2021-05-01",
      "stock_id": "2483",
      "open": 22.75,
      "max": 23,
      "min": 18,
      "close": 19.85,
      "Trading_Volume": 5486486,
      "Trading_money": 113744097
    },
    {
      "date": "2021-06-01",
      "stock_id": "2483",
      "open": 19.9,
      "max": 23.8,
      "min": 19.6,
      "close": 22.3,
      "Trading_Volume": 4510467,
      "Trading_money": 99926536
    },
    {
      "date": "2021-07-01",
      "stock_id": "2483",
      "open": 22.3,
      "max": 30,
      "min": 22.1,
      "close": 25.6,
      "Trading_Volume": 43264566,
      "Trading_money": 1157769212
    },
    {
      "date": "2021-08-01",
      "stock_id": "2483",
      "open": 25.6,
      "max": 28.45,
      "min": 23.2,
      "close": 28,
      "Trading_Volume": 16179501,
      "Trading_money": 426739086
    },
    {
      "date": "2021-09-01",
      "stock_id": "2483",
      "open": 28,
      "max": 31.45,
      "min": 24.5,
      "close": 25.25,
      "Trading_Volume": 39189218,
      "Trading_money": 1114997524
    },
    {
      "date": "2021-10-01",
      "stock_id": "2483",
      "open": 25.1,
      "max": 25.7,
      "min": 22.5,
      "close": 25.4,
      "Trading_Volume": 6576364,
      "Trading_money": 157565869
    },
    {
      "date": "2021-11-01",
      "stock_id": "2483",
      "open": 25.9,
      "max": 26.1,
      "min": 22.85,
      "close": 24.35,
      "Trading_Volume": 6644199,
      "Trading_money": 163522947
    },
    {
      "date": "2021-12-01",
      "stock_id": "2483",
      "open": 23.9,
      "max": 27.7,
      "min": 23.6,
      "close": 26.75,
      "Trading_Volume": 29986290,
      "Trading_money": 796689947
    },
    {
      "date": "2022-01-01",
      "stock_id": "2483",
      "open": 26.6,
      "max": 26.95,
      "min": 23.3,
      "close": 23.5,
      "Trading_Volume": 5674972,
      "Trading_money": 144596861
    },
    {
      "date": "2022-02-01",
      "stock_id": "2483",
      "open": 23.55,
      "max": 24.95,
      "min": 23.5,
      "close": 23.6,
      "Trading_Volume": 1550260,
      "Trading_money": 37420542
    },
    {
      "date": "2022-03-01",
      "stock_id": "2483",
      "open": 23.6,
      "max": 24.5,
      "min": 22.7,
      "close": 23.55,
      "Trading_Volume": 2834551,
      "Trading_money": 67225290
    },
    {
      "date": "2022-04-01",
      "stock_id": "2483",
      "open": 23.45,
      "max": 24.1,
      "min": 21.9,
      "close": 22.8,
      "Trading_Volume": 1545222,
      "Trading_money": 35721140
    },
    {
      "date": "2022-05-01",
      "stock_id": "2483",
      "open": 22.7,
      "max": 27.5,
      "min": 22.5,
      "close": 26.5,
      "Trading_Volume": 20070228,
      "Trading_money": 517654268
    },
    {
      "date": "2022-06-01",
      "stock_id": "2483",
      "open": 26.9,
      "max": 27.5,
      "min": 24.55,
      "close": 26.35,
      "Trading_Volume": 21093157,
      "Trading_money": 554035203
    },
    {
      "date": "2022-07-01",
      "stock_id": "2483",
      "open": 26.55,
      "max": 30.1,
      "min": 23.2,
      "close": 25.25,
      "Trading_Volume": 33177030,
      "Trading_money": 886040596
    },
    {
      "date": "2022-08-01",
      "stock_id": "2483",
      "open": 25.3,
      "max": 25.55,
      "min": 23.3,
      "close": 24.45,
      "Trading_Volume": 5708054,
      "Trading_money": 139198908
    },
    {
      "date": "2022-09-01",
      "stock_id": "2483",
      "open": 24.3,
      "max": 32.8,
      "min": 24.1,
      "close": 29.75,
      "Trading_Volume": 65035428,
      "Trading_money": 1965637141
    },
    {
      "date": "2022-10-01",
      "stock_id": "2483",
      "open": 29.45,
      "max": 31.3,
      "min": 22.6,
      "close": 23.3,
      "Trading_Volume": 22355468,
      "Trading_money": 598580344
    },
    {
      "date": "2022-11-01",
      "stock_id": "2483",
      "open": 23.5,
      "max": 27.3,
      "min": 23.3,
      "close": 25.5,
      "Trading_Volume": 9984410,
      "Trading_money": 246320308
    },
    {
      "date": "2022-12-01",
      "stock_id": "2483",
      "open": 25.5,
      "max": 26.8,
      "min": 23.7,
      "close": 24,
      "Trading_Volume": 6183894,
      "Trading_money": 155810321
    },
    {
      "date": "2023-01-01",
      "stock_id": "2483",
      "open": 24.35,
      "max": 24.65,
      "min": 23.9,
      "close": 24.25,
      "Trading_Volume": 1694409,
      "Trading_money": 41108779
    },
    {
      "date": "2023-02-01",
      "stock_id": "2483",
      "open": 24.5,
      "max": 26.6,
      "min": 24.45,
      "close": 26.05,
      "Trading_Volume": 6152533,
      "Trading_money": 157431547
    },
    {
      "date": "2023-03-01",
      "stock_id": "2483",
      "open": 25.8,
      "max": 27.6,
      "min": 25.15,
      "close": 25.55,
      "Trading_Volume": 6230603,
      "Trading_money": 164207598
    },
    {
      "date": "2023-04-01",
      "stock_id": "2483",
      "open": 25.55,
      "max": 28.7,
      "min": 25.25,
      "close": 27,
      "Trading_Volume": 11098580,
      "Trading_money": 304217198
    },
    {
      "date": "2023-05-01",
      "stock_id": "2483",
      "open": 27.1,
      "max": 29.4,
      "min": 25.8,
      "close": 29.1,
      "Trading_Volume": 7238212,
      "Trading_money": 200825459
    },
    {
      "date": "2023-06-01",
      "stock_id": "2483",
      "open": 29.15,
      "max": 29.35,
      "min": 26.45,
      "close": 26.75,
      "Trading_Volume": 8207464,
      "Trading_money": 227958557
    },
    {
      "date": "2023-07-01",
      "stock_id": "2483",
      "open": 26.95,
      "max": 27.25,
      "min": 24.7,
      "close": 25.4,
      "Trading_Volume": 5053780,
      "Trading_money": 129826122
    },
    {
      "date": "2023-08-01",
      "stock_id": "2483",
      "open": 25.4,
      "max": 25.4,
      "min": 23.5,
      "close": 24.5,
      "Trading_Volume": 2066228,
      "Trading_money": 50356052
    },
    {
      "date": "2023-09-01",
      "stock_id": "2483",
      "open": 24.4,
      "max": 26,
      "min": 24.15,
      "close": 24.95,
      "Trading_Volume": 2497415,
      "Trading_money": 62346585
    },
    {
      "date": "2023-10-01",
      "stock_id": "2483",
      "open": 25,
      "max": 25.2,
      "min": 23.2,
      "close": 23.3,
      "Trading_Volume": 1077855,
      "Trading_money": 26091185
    },
    {
      "date": "2023-11-01",
      "stock_id": "2483",
      "open": 23.45,
      "max": 24.5,
      "min": 23.35,
      "close": 24.1,
      "Trading_Volume": 1189200,
      "Trading_money": 28481836
    },
    {
      "date": "2023-12-01",
      "stock_id": "2483",
      "open": 24.15,
      "max": 25.2,
      "min": 23.9,
      "close": 24.1,
      "Trading_Volume": 1708962,
      "Trading_money": 41539064
    },
    {
      "date": "2024-01-01",
      "stock_id": "2483",
      "open": 24.1,
      "max": 24.15,
      "min": 23.45,
      "close": 23.6,
      "Trading_Volume": 1283978,
      "Trading_money": 30532878
    },
    {
      "date": "2024-02-01",
      "stock_id": "2483",
      "open": 23.6,
      "max": 24.4,
      "min": 23.4,
      "close": 23.8,
      "Trading_Volume": 1048677,
      "Trading_money": 25089845
    },
    {
      "date": "2024-03-01",
      "stock_id": "2483",
      "open": 23.75,
      "max": 24.5,
      "min": 22.6,
      "close": 23.5,
      "Trading_Volume": 3883579,
      "Trading_money": 90751595
    },
    {
      "date": "2024-04-01",
      "stock_id": "2483",
      "open": 24.15,
      "max": 25,
      "min": 22.6,
      "close": 23.4,
      "Trading_Volume": 2817005,
      "Trading_money": 67150049
    },
    {
      "date": "2024-05-01",
      "stock_id": "2483",
      "open": 23.35,
      "max": 27.7,
      "min": 23.35,
      "close": 26.5,
      "Trading_Volume": 14733693,
      "Trading_money": 388535476
    },
    {
      "date": "2024-06-01",
      "stock_id": "2483",
      "open": 26.9,
      "max": 27.25,
      "min": 24.9,
      "close": 26.75,
      "Trading_Volume": 5436783,
      "Trading_money": 140251033
    },
    {
      "date": "2024-07-01",
      "stock_id": "2483",
      "open": 27,
      "max": 28.05,
      "min": 26.15,
      "close": 26.8,
      "Trading_Volume": 4579447,
      "Trading_money": 124188889
    }
  ]
}
