{
  "data": [
    {
      "date": "2021-01-01",
      "stock_id": "4154",
      "open": 26.6,
      "max": 29.45,
      "min": 26,
      "close": 27.8,
      "Trading_Volume": 375000,
      "Trading_money": 10429100
    },
    {
      "date": "2021-02-01",
      "stock_id": "4154",
      "open": 28.6,
      "max": 29,
      "min": 26.55,
      "close": 27.9,
      "Trading_Volume": 120000,
      "Trading_money": 3355650
    },
    {
      "date": "2021-03-01",
      "stock_id": "4154",
      "open": 28,
      "max": 30.65,
      "min": 27.4,
      "close": 28.65,
      "Trading_Volume": 642000,
      "Trading_money": 18273550
    },
    {
      "date": "2021-04-01",
      "stock_id": "4154",
      "open": 28,
      "max": 29.8,
      "min": 26.5,
      "close": 27.95,
      "Trading_Volume": 442000,
      "Trading_money": 12366800
    },
    {
      "date": "2021-05-01",
      "stock_id": "4154",
      "open": 27,
      "max": 28.95,
      "min": 24.8,
      "close": 27,
      "Trading_Volume": 277000,
      "Trading_money": 7492550
    },
    {
      "date": "2021-06-01",
      "stock_id": "4154",
      "open": 28,
      "max": 29.15,
      "min": 24.05,
      "close": 26.25,
      "Trading_Volume": 155000,
      "Trading_money": 4091350
    },
    {
      "date": "2021-07-01",
      "stock_id": "4154",
      "open": 25.55,
      "max": 26.2,
      "min": 24,
      "close": 24.3,
      "Trading_Volume": 155000,
      "Trading_money": 3848500
    },
    {
      "date": "2021-08-01",
      "stock_id": "4154",
      "open": 24.55,
      "max": 44.35,
      "min": 24,
      "close": 39.1,
      "Trading_Volume": 2784000,
      "Trading_money": 95263750
    },
    {
      "date": "2021-09-01",
      "stock_id": "4154",
      "open": 42.25,
      "max": 58.7,
      "min": 38.2,
      "close": 49.5,
      "Trading_Volume": 5062000,
      "Trading_money": 251255900
    },
    {
      "date": "2021-10-01",
      "stock_id": "4154",
      "open": 48.7,
      "max": 58.3,
      "min": 48.3,
      "close": 55.3,
      "Trading_Volume": 2644000,
      "Trading_money": 143816950
    },
    {
      "date": "2021-11-01",
      "stock_id": "4154",
      "open": 55,
      "max": 63.6,
      "min": 53.2,
      "close": 61.6,
      "Trading_Volume": 1120000,
      "Trading_money": 64961200
    },
    {
      "date": "2021-12-01",
      "stock_id": "4154",
      "open": 61.6,
      "max": 62.3,
      "min": 47.2,
      "close": 53.5,
      "Trading_Volume": 784000,
      "Trading_money": 42609950
    },
    {
      "date": "2022-01-01",
      "stock_id": "4154",
      "open": 50.4,
      "max": 53.7,
      "min": 38,
      "close": 41.4,
      "Trading_Volume": 567000,
      "Trading_money": 25240650
    },
    {
      "date": "2022-02-01",
      "stock_id": "4154",
      "open": 41.4,
      "max": 45.7,
      "min": 39.6,
      "close": 41.15,
      "Trading_Volume": 207000,
      "Trading_money": 8719800
    },
    {
      "date": "2022-03-01",
      "stock_id": "4154",
      "open": 40.8,
      "max": 43.7,
      "min": 39,
      "close": 40.7,
      "Trading_Volume": 142000,
      "Trading_money": 5809500
    },
    {
      "date": "2022-04-01",
      "stock_id": "4154",
      "open": 41.8,
      "max": 41.8,
      "min": 38,
      "close": 40,
      "Trading_Volume": 260000,
      "Trading_money": 10386200
    },
    {
      "date": "2022-05-01",
      "stock_id": "4154",
      "open": 39.8,
      "max": 47.5,
      "min": 38,
      "close": 39.25,
      "Trading_Volume": 824000,
      "Trading_money": 34347750
    },
    {
      "date": "2022-06-01",
      "stock_id": "4154",
      "open": 39.4,
      "max": 48.3,
      "min": 39,
      "close": 45.4,
      "Trading_Volume": 450000,
      "Trading_money": 20118100
    },
    {
      "date": "2022-07-01",
      "stock_id": "4154",
      "open": 46.35,
      "max": 47.1,
      "min": 41,
      "close": 44.3,
      "Trading_Volume": 341000,
      "Trading_money": 15099400
    },
    {
      "date": "2022-08-01",
      "stock_id": "4154",
      "open": 44.35,
      "max": 46.5,
      "min": 42.7,
      "close": 45.2,
      "Trading_Volume": 412000,
      "Trading_money": 18463200
    },
    {
      "date": "2022-09-01",
      "stock_id": "4154",
      "open": 45.1,
      "max": 46.7,
      "min": 43.4,
      "close": 45.8,
      "Trading_Volume": 292000,
      "Trading_money": 13057700
    },
    {
      "date": "2022-10-01",
      "stock_id": "4154",
      "open": 44.5,
      "max": 47.2,
      "min": 41.1,
      "close": 44,
      "Trading_Volume": 601000,
      "Trading_money": 26969800
    },
    {
      "date": "2022-11-01",
      "stock_id": "4154",
      "open": 44,
      "max": 45.45,
      "min": 40.3,
      "close": 42.75,
      "Trading_Volume": 1010000,
      "Trading_money": 44326800
    },
    {
      "date": "2022-12-01",
      "stock_id": "4154",
      "open": 43,
      "max": 43.9,
      "min": 39.3,
      "close": 40,
      "Trading_Volume": 97000,
      "Trading_money": 3949350
    },
    {
      "date": "2023-01-01",
      "stock_id": "4154",
      "open": 38.7,
      "max": 42,
      "min": 36.3,
      "close": 38.65,
      "Trading_Volume": 251000,
      "Trading_money": 9719350
    },
    {
      "date": "2023-02-01",
      "stock_id": "4154",
      "open": 37.5,
      "max": 38.35,
      "min": 34,
      "close": 35,
      "Trading_Volume": 394000,
      "Trading_money": 14346450
    },
    {
      "date": "2023-03-01",
      "stock_id": "4154",
      "open": 35,
      "max": 36.8,
      "min": 33.65,
      "close": 34.1,
      "Trading_Volume": 740000,
      "Trading_money": 25907100
    },
    {
      "date": "2023-04-01",
      "stock_id": "4154",
      "open": 34.9,
      "max": 34.95,
      "min": 27,
      "close": 30.9,
      "Trading_Volume": 736000,
      "Trading_money": 22214050
    },
    {
      "date": "2023-05-01",
      "stock_id": "4154",
      "open": 30.8,
      "max": 31,
      "min": 28.7,
      "close": 30.9,
      "Trading_Volume": 64000,
      "Trading_money": 1914000
    },
    {
      "date": "2023-06-01",
      "stock_id": "4154",
      "open": 28.7,
      "max": 31.05,
      "min": 25,
      "close": 25.4,
      "Trading_Volume": 300000,
      "Trading_money": 8177550
    },
    {
      "date": "2023-07-01",
      "stock_id": "4154",
      "open": 25.4,
      "max": 25.4,
      "min": 9.63,
      "close": 10.2,
      "Trading_Volume": 5316000,
      "Trading_money": 74933320
    },
    {
      "date": "2023-08-01",
      "stock_id": "4154",
      "open": 10.1,
      "max": 18.75,
      "min": 10,
      "close": 15,
      "Trading_Volume": 4795000,
      "Trading_money": 71779050
    },
    {
      "date": "2023-09-01",
      "stock_id": "4154",
      "open": 15.95,
      "max": 18.15,
      "min": 14.35,
      "close": 14.7,
      "Trading_Volume": 2743000,
      "Trading_money": 45342200
    },
    {
      "date": "2023-10-01",
      "stock_id": "4154",
      "open": 14.7,
      "max": 14.95,
      "min": 11.3,
      "close": 14.85,
      "Trading_Volume": 1540000,
      "Trading_money": 20802550
    },
    {
      "date": "2023-11-01",
      "stock_id": "4154",
      "open": 14.8,
      "max": 15.55,
      "min": 12.5,
      "close": 14.2,
      "Trading_Volume": 1253000,
      "Trading_money": 17514200
    },
    {
      "date": "2023-12-01",
      "stock_id": "4154",
      "open": 14.8,
      "max": 16.55,
      "min": 13.5,
      "close": 15.25,
      "Trading_Volume": 2835000,
      "Trading_money": 42696000
    },
    {
      "date": "2024-01-01",
      "stock_id": "4154",
      "open": 15,
      "max": 16.05,
      "min": 14.3,
      "close": 15.15,
      "Trading_Volume": 1753000,
      "Trading_money": 26932400
    },
    {
      "date": "2024-02-01",
      "stock_id": "4154",
      "open": 14.8,
      "max": 15.3,
      "min": 13.8,
      "close": 14.95,
      "Trading_Volume": 754000,
      "Trading_money": 11081350
    },
    {
      "date": "2024-03-01",
      "stock_id": "4154",
      "open": 15,
      "max": 15.25,
      "min": 13.5,
      "close": 13.5,
      "Trading_Volume": 1231000,
      "Trading_money": 18051700
    },
    {
      "date": "2024-04-01",
      "stock_id": "4154",
      "open": 13.35,
      "max": 13.85,
      "min": 12.8,
      "close": 13.05,
      "Trading_Volume": 376000,
      "Trading_money": 4995550
    },
    {
      "date": "2024-05-01",
      "stock_id": "4154",
      "open": 13.3,
      "max": 14.1,
      "min": 12.5,
      "close": 13.05,
      "Trading_Volume": 655000,
      "Trading_money": 8568200
    },
    {
      "date": "2024-06-01",
      "stock_id": "4154",
      "open": 13,
      "max": 15.8,
      "min": 12.8,
      "close": 14.05,
      "Trading_Volume": 1064000,
      "Trading_money": 15343550
    },
    {
      "date": "2024-07-01",
      "stock_id": "4154",
      "open": 14.3,
      "max": 15.9,
      "min": 14.05,
      "close": 15.55,
      "Trading_Volume": 620000,
      "Trading_money": 9331650
    }
  ]
}
