{
  "data": [
    {
      "date": "2021-01-01",
      "stock_id": "6168",
      "open": 19,
      "max": 21.2,
      "min": 16.35,
      "close": 16.75,
      "Trading_Volume": 145831284,
      "Trading_money": 2756802295
    },
    {
      "date": "2021-02-01",
      "stock_id": "6168",
      "open": 16.6,
      "max": 18.7,
      "min": 16.3,
      "close": 18.05,
      "Trading_Volume": 22865971,
      "Trading_money": 403467457
    },
    {
      "date": "2021-03-01",
      "stock_id": "6168",
      "open": 18.15,
      "max": 20.45,
      "min": 17.15,
      "close": 19.45,
      "Trading_Volume": 54243687,
      "Trading_money": 1029508778
    },
    {
      "date": "2021-04-01",
      "stock_id": "6168",
      "open": 20,
      "max": 24.8,
      "min": 19.65,
      "close": 23,
      "Trading_Volume": 152384744,
      "Trading_money": 3439190215
    },
    {
      "date": "2021-05-01",
      "stock_id": "6168",
      "open": 23,
      "max": 23,
      "min": 16,
      "close": 20.75,
      "Trading_Volume": 53556178,
      "Trading_money": 1033587212
    },
    {
      "date": "2021-06-01",
      "stock_id": "6168",
      "open": 20.9,
      "max": 24.5,
      "min": 20.45,
      "close": 24.3,
      "Trading_Volume": 83147932,
      "Trading_money": 1884943300
    },
    {
      "date": "2021-07-01",
      "stock_id": "6168",
      "open": 24,
      "max": 36.75,
      "min": 21.95,
      "close": 28.9,
      "Trading_Volume": 412752315,
      "Trading_money": 12520846439
    },
    {
      "date": "2021-08-01",
      "stock_id": "6168",
      "open": 29.1,
      "max": 33.85,
      "min": 24.8,
      "close": 27.85,
      "Trading_Volume": 171265184,
      "Trading_money": 5124193685
    },
    {
      "date": "2021-09-01",
      "stock_id": "6168",
      "open": 27.9,
      "max": 29.75,
      "min": 23.85,
      "close": 24.2,
      "Trading_Volume": 55036774,
      "Trading_money": 1492320153
    },
    {
      "date": "2021-10-01",
      "stock_id": "6168",
      "open": 24,
      "max": 25.9,
      "min": 22.1,
      "close": 25,
      "Trading_Volume": 39151907,
      "Trading_money": 947595327
    },
    {
      "date": "2021-11-01",
      "stock_id": "6168",
      "open": 25.45,
      "max": 30.25,
      "min": 25,
      "close": 27.3,
      "Trading_Volume": 141164787,
      "Trading_money": 3965695155
    },
    {
      "date": "2021-12-01",
      "stock_id": "6168",
      "open": 26.8,
      "max": 29.25,
      "min": 26.6,
      "close": 27.4,
      "Trading_Volume": 84294423,
      "Trading_money": 2351842076
    },
    {
      "date": "2022-01-01",
      "stock_id": "6168",
      "open": 27.65,
      "max": 27.65,
      "min": 24.3,
      "close": 24.5,
      "Trading_Volume": 29697024,
      "Trading_money": 782374034
    },
    {
      "date": "2022-02-01",
      "stock_id": "6168",
      "open": 24.65,
      "max": 26.75,
      "min": 24.35,
      "close": 24.55,
      "Trading_Volume": 11990413,
      "Trading_money": 308408734
    },
    {
      "date": "2022-03-01",
      "stock_id": "6168",
      "open": 25,
      "max": 25.35,
      "min": 22.05,
      "close": 24.3,
      "Trading_Volume": 14116048,
      "Trading_money": 335326281
    },
    {
      "date": "2022-04-01",
      "stock_id": "6168",
      "open": 24.25,
      "max": 24.25,
      "min": 19.7,
      "close": 21.1,
      "Trading_Volume": 9372766,
      "Trading_money": 208125753
    },
    {
      "date": "2022-05-01",
      "stock_id": "6168",
      "open": 20.8,
      "max": 23.5,
      "min": 20.3,
      "close": 23.3,
      "Trading_Volume": 7436232,
      "Trading_money": 163980184
    },
    {
      "date": "2022-06-01",
      "stock_id": "6168",
      "open": 23.45,
      "max": 24,
      "min": 19.95,
      "close": 20.05,
      "Trading_Volume": 7699794,
      "Trading_money": 168767279
    },
    {
      "date": "2022-07-01",
      "stock_id": "6168",
      "open": 20.15,
      "max": 20.15,
      "min": 18.15,
      "close": 19.25,
      "Trading_Volume": 8184360,
      "Trading_money": 156467698
    },
    {
      "date": "2022-08-01",
      "stock_id": "6168",
      "open": 19.25,
      "max": 21.4,
      "min": 18.5,
      "close": 19.9,
      "Trading_Volume": 11034727,
      "Trading_money": 222660004
    },
    {
      "date": "2022-09-01",
      "stock_id": "6168",
      "open": 19.85,
      "max": 19.9,
      "min": 15.5,
      "close": 16.15,
      "Trading_Volume": 7129018,
      "Trading_money": 126885045
    },
    {
      "date": "2022-10-01",
      "stock_id": "6168",
      "open": 16.4,
      "max": 17.15,
      "min": 14.6,
      "close": 15.5,
      "Trading_Volume": 4688176,
      "Trading_money": 74268776
    },
    {
      "date": "2022-11-01",
      "stock_id": "6168",
      "open": 15.4,
      "max": 18.45,
      "min": 15.4,
      "close": 18.4,
      "Trading_Volume": 10975568,
      "Trading_money": 190609387
    },
    {
      "date": "2022-12-01",
      "stock_id": "6168",
      "open": 18.65,
      "max": 19.25,
      "min": 17.4,
      "close": 17.6,
      "Trading_Volume": 6415328,
      "Trading_money": 117728847
    },
    {
      "date": "2023-01-01",
      "stock_id": "6168",
      "open": 17.5,
      "max": 18.7,
      "min": 17.5,
      "close": 18.5,
      "Trading_Volume": 2918778,
      "Trading_money": 52541089
    },
    {
      "date": "2023-02-01",
      "stock_id": "6168",
      "open": 18.6,
      "max": 22.4,
      "min": 18.45,
      "close": 21.6,
      "Trading_Volume": 15421236,
      "Trading_money": 318342478
    },
    {
      "date": "2023-03-01",
      "stock_id": "6168",
      "open": 21.75,
      "max": 27.5,
      "min": 21.5,
      "close": 25.85,
      "Trading_Volume": 59605907,
      "Trading_money": 1478365457
    },
    {
      "date": "2023-04-01",
      "stock_id": "6168",
      "open": 25.7,
      "max": 26.45,
      "min": 23.95,
      "close": 25.55,
      "Trading_Volume": 20168719,
      "Trading_money": 513412198
    },
    {
      "date": "2023-05-01",
      "stock_id": "6168",
      "open": 25.6,
      "max": 25.95,
      "min": 22.6,
      "close": 23.5,
      "Trading_Volume": 12783605,
      "Trading_money": 305182881
    },
    {
      "date": "2023-06-01",
      "stock_id": "6168",
      "open": 23.5,
      "max": 25.55,
      "min": 23.15,
      "close": 24.1,
      "Trading_Volume": 18376515,
      "Trading_money": 451658390
    },
    {
      "date": "2023-07-01",
      "stock_id": "6168",
      "open": 24.55,
      "max": 26.75,
      "min": 22.15,
      "close": 23,
      "Trading_Volume": 42938696,
      "Trading_money": 1075611042
    },
    {
      "date": "2023-08-01",
      "stock_id": "6168",
      "open": 23.1,
      "max": 27.85,
      "min": 21.5,
      "close": 26.2,
      "Trading_Volume": 94105660,
      "Trading_money": 2458043570
    },
    {
      "date": "2023-09-01",
      "stock_id": "6168",
      "open": 26.3,
      "max": 26.85,
      "min": 22.5,
      "close": 22.95,
      "Trading_Volume": 49103612,
      "Trading_money": 1186872815
    },
    {
      "date": "2023-10-01",
      "stock_id": "6168",
      "open": 23.1,
      "max": 29.7,
      "min": 23.1,
      "close": 26.05,
      "Trading_Volume": 241141662,
      "Trading_money": 6423733145
    },
    {
      "date": "2023-11-01",
      "stock_id": "6168",
      "open": 26.05,
      "max": 28.2,
      "min": 24.1,
      "close": 27.35,
      "Trading_Volume": 120539599,
      "Trading_money": 3229041751
    },
    {
      "date": "2023-12-01",
      "stock_id": "6168",
      "open": 27.25,
      "max": 29.25,
      "min": 26,
      "close": 26.35,
      "Trading_Volume": 85556753,
      "Trading_money": 2370585002
    },
    {
      "date": "2024-01-01",
      "stock_id": "6168",
      "open": 26.35,
      "max": 27.35,
      "min": 25.05,
      "close": 25.25,
      "Trading_Volume": 41047433,
      "Trading_money": 1074454173
    },
    {
      "date": "2024-02-01",
      "stock_id": "6168",
      "open": 25.25,
      "max": 30.2,
      "min": 24.5,
      "close": 26.8,
      "Trading_Volume": 76751631,
      "Trading_money": 2145117251
    },
    {
      "date": "2024-03-01",
      "stock_id": "6168",
      "open": 26.8,
      "max": 26.8,
      "min": 23.85,
      "close": 24.15,
      "Trading_Volume": 27464830,
      "Trading_money": 692432715
    },
    {
      "date": "2024-04-01",
      "stock_id": "6168",
      "open": 24.15,
      "max": 24.6,
      "min": 22.1,
      "close": 23.9,
      "Trading_Volume": 17777549,
      "Trading_money": 419686051
    },
    {
      "date": "2024-05-01",
      "stock_id": "6168",
      "open": 23.9,
      "max": 26.2,
      "min": 23.3,
      "close": 24.65,
      "Trading_Volume": 43747406,
      "Trading_money": 1089791268
    },
    {
      "date": "2024-06-01",
      "stock_id": "6168",
      "open": 24.8,
      "max": 24.95,
      "min": 23.35,
      "close": 23.6,
      "Trading_Volume": 14364744,
      "Trading_money": 345086952
    },
    {
      "date": "2024-07-01",
      "stock_id": "6168",
      "open": 23.65,
      "max": 24.95,
      "min": 23.4,
      "close": 24.55,
      "Trading_Volume": 11038812,
      "Trading_money": 268938939
    }
  ]
}
